_web3_hook/__init__.py
cns/__init__.py
cns/cns.py
cns/exceptions.py
cns/py.typed
cns/utils.py
conflux_web3/__init__.py
conflux_web3/client.py
conflux_web3/exceptions.py
conflux_web3/main.py
conflux_web3/method.py
conflux_web3/py.typed
conflux_web3/txpool.py
conflux_web3/utils.py
conflux_web3/_utils/__init__.py
conflux_web3/_utils/abi.py
conflux_web3/_utils/cns.py
conflux_web3/_utils/contracts.py
conflux_web3/_utils/decorators.py
conflux_web3/_utils/disabled_eth_apis.py
conflux_web3/_utils/events.py
conflux_web3/_utils/method_formatters.py
conflux_web3/_utils/normalizers.py
conflux_web3/_utils/rpc_abi.py
conflux_web3/_utils/transactions.py
conflux_web3/contract/__init__.py
conflux_web3/contract/caller.py
conflux_web3/contract/constructor.py
conflux_web3/contract/event.py
conflux_web3/contract/function.py
conflux_web3/contract/metadata/AdminControl.json
conflux_web3/contract/metadata/ConfluxContext.json
conflux_web3/contract/metadata/Create2Factory.json
conflux_web3/contract/metadata/CrossSpaceCall.json
conflux_web3/contract/metadata/ENS.json
conflux_web3/contract/metadata/ERC1820.json
conflux_web3/contract/metadata/ERC20.json
conflux_web3/contract/metadata/ETHRegistrarController.json
conflux_web3/contract/metadata/Faucet.json
conflux_web3/contract/metadata/NameWrapper.json
conflux_web3/contract/metadata/ParamsControl.json
conflux_web3/contract/metadata/PoSRegister.json
conflux_web3/contract/metadata/RESOLVER.json
conflux_web3/contract/metadata/SponsorWhitelistControl.json
conflux_web3/contract/metadata/Staking.json
conflux_web3/contract/metadata/__init__.py
conflux_web3/dev/__init__.py
conflux_web3/middleware/__init__.py
conflux_web3/middleware/base.py
conflux_web3/middleware/cache.py
conflux_web3/middleware/names.py
conflux_web3/middleware/pending.py
conflux_web3/middleware/wallet.py
conflux_web3/providers/__init__.py
conflux_web3/providers/rpc.py
conflux_web3/types/__init__.py
conflux_web3/types/transaction_hash.py
conflux_web3/utils/__init__.py
conflux_web3-1.4.4.dist-info/METADATA
conflux_web3-1.4.4.dist-info/WHEEL
conflux_web3-1.4.4.dist-info/top_level.txt
conflux_web3-1.4.4.dist-info/RECORD
