Metadata-Version: 2.1
Name: conflux-web3
Version: 1.4.4
Summary: Python SDK for Conflux network
Home-page: https://github.com/conflux-chain/python-conflux-sdk
Author: Conflux-Dev
Author-email: wenda.zhang@confluxnetwork.org
Keywords: python,conflux,blockchain
Classifier: Programming Language :: Python :: 3
Classifier: Programming Language :: Python :: 3.8
Classifier: Programming Language :: Python :: 3.9
Classifier: Programming Language :: Python :: 3.10
Classifier: Programming Language :: Python :: 3.11
Classifier: Programming Language :: Python :: 3.12
Classifier: Programming Language :: Python :: 3.13
Classifier: Operating System :: MacOS :: MacOS X
Classifier: Operating System :: Microsoft :: Windows
Requires-Dist: web3==7.11.1
Requires-Dist: cfx-address<1.3.0,>=1.2.4
Requires-Dist: cfx-account<1.3.0,>=1.2.2
Requires-Dist: cfx-utils<1.2.0,>=1.0.5
Requires-Dist: typing-extensions<=4.13.2
Provides-Extra: dev
Requires-Dist: docker<8,>=7.1.0; extra == "dev"
Requires-Dist: pytest<9,>=8; extra == "dev"
Requires-Dist: pytest-xdist<4,>=3; extra == "dev"
Requires-Dist: typing-extensions; extra == "dev"
Requires-Dist: pytest-cov; extra == "dev"
Requires-Dist: ipfshttpclient==0.8.0a2; extra == "dev"
Requires-Dist: python-dotenv; extra == "dev"
Requires-Dist: setuptools; extra == "dev"
Requires-Dist: pydantic<3,>=2.6.0; extra == "dev"
Requires-Dist: cfx-address>=1.2.0; extra == "dev"
Requires-Dist: pytest-xdist; extra == "dev"
Requires-Dist: pytest-order; extra == "dev"
Requires-Dist: black<23.0,>=22.1.0; extra == "dev"
Requires-Dist: jupyter-book; extra == "dev"
Requires-Dist: mmg==2.0.0; extra == "dev"
Requires-Dist: sphinx-autodoc-typehints; extra == "dev"
Requires-Dist: wheel; extra == "dev"
Requires-Dist: bumpversion; extra == "dev"
Requires-Dist: twine; extra == "dev"
Provides-Extra: docs
Requires-Dist: jupyter-book; extra == "docs"
Requires-Dist: mmg==2.0.0; extra == "docs"
Requires-Dist: sphinx-autodoc-typehints; extra == "docs"
Requires-Dist: wheel; extra == "docs"
Provides-Extra: ipfs
Requires-Dist: ipfshttpclient==0.8.0a2; extra == "ipfs"
Provides-Extra: linter
Requires-Dist: black<23.0,>=22.1.0; extra == "linter"
Provides-Extra: tester
Requires-Dist: docker<8,>=7.1.0; extra == "tester"
Requires-Dist: pytest<9,>=8; extra == "tester"
Requires-Dist: pytest-xdist<4,>=3; extra == "tester"
Requires-Dist: typing-extensions; extra == "tester"
Requires-Dist: pytest-cov; extra == "tester"
Requires-Dist: ipfshttpclient==0.8.0a2; extra == "tester"
Requires-Dist: python-dotenv; extra == "tester"
Requires-Dist: setuptools; extra == "tester"
Requires-Dist: pydantic<3,>=2.6.0; extra == "tester"
Requires-Dist: cfx-address>=1.2.0; extra == "tester"
Requires-Dist: pytest-xdist; extra == "tester"
Requires-Dist: pytest-order; extra == "tester"
